nanosignfs/__init__.py
nanosignfs/config.py
nanosignfs/core.py
nanosignfs/signer.py
nanosignfs-0.1.1.dist-info/METADATA
nanosignfs-0.1.1.dist-info/WHEEL
nanosignfs-0.1.1.dist-info/top_level.txt
nanosignfs-0.1.1.dist-info/RECORD
