Metadata-Version: 2.1
Name: nanosignfs
Version: 0.1.1
Summary: A Linux FUSE filesystem that signs files on write using GPG (PKI), ideal for nano-data pipelines.
Home-page: https://github.com/yourusername/nanosignfs
Author: Raghava Chellu
Author-email: raghava.chellu@gmail.com
Keywords: fuse,gpg,filesystem,cryptography,signing,pki,nano-data,virtual filesystem,python-fuse,linux-filesystem
Classifier: Programming Language :: Python :: 3
Classifier: Operating System :: POSIX :: Linux
Classifier: License :: OSI Approved :: MIT License
Classifier: Topic :: Security :: Cryptography
Classifier: Topic :: System :: Filesystems
Requires-Python: >=3.7
Requires-Dist: fusepy
Requires-Dist: python-gnupg
